{
  "experiment": "MoTE CUB B0-Inc20 five-seed reproduction",
  "dataset": "CUB-200-2011",
  "setting": "B0-Inc20",
  "seeds": [
    1991,
    1992,
    1993,
    1994,
    1995
  ],
  "per_seed": [
    {
      "seed": 1991,
      "log": "/workspace/runs/mote_cub_5seed_logs/mote_cub_seed1991_2026-07-02_0821.log",
      "average_accuracy_cnn": 91.78599999999999,
      "last_accuracy_cnn": 87.31,
      "forgetting_cnn": 4.14222222222222,
      "top1_curve": [
        96.58,
        95.85,
        94.08,
        93.64,
        91.87,
        91.27,
        89.93,
        89.28,
        88.05,
        87.31
      ],
      "top5_curve": [
        100.0,
        99.48,
        99.13,
        99.09,
        99.04,
        98.88,
        98.76,
        98.75,
        98.47,
        98.36
      ]
    },
    {
      "seed": 1992,
      "log": "/workspace/runs/mote_cub_5seed_logs/mote_cub_seed1992_2026-07-02_0834.log",
      "average_accuracy_cnn": 91.32400000000003,
      "last_accuracy_cnn": 87.21,
      "forgetting_cnn": 4.495555555555553,
      "top1_curve": [
        96.16,
        94.48,
        94.22,
        93.94,
        91.91,
        90.2,
        89.44,
        88.1,
        87.58,
        87.21
      ],
      "top5_curve": [
        100.0,
        99.83,
        99.37,
        99.19,
        99.01,
        98.8,
        98.65,
        98.41,
        98.37,
        98.38
      ]
    },
    {
      "seed": 1993,
      "log": "/workspace/runs/mote_cub_5seed_logs/mote_cub_seed1993_2026-07-02_0847.log",
      "average_accuracy_cnn": 91.502,
      "last_accuracy_cnn": 87.12,
      "forgetting_cnn": 4.329999999999998,
      "top1_curve": [
        96.46,
        96.07,
        94.26,
        93.13,
        91.96,
        90.51,
        89.17,
        88.26,
        88.08,
        87.12
      ],
      "top5_curve": [
        99.83,
        99.48,
        99.3,
        99.22,
        99.06,
        98.96,
        98.91,
        98.72,
        98.6,
        98.39
      ]
    },
    {
      "seed": 1994,
      "log": "/workspace/runs/mote_cub_5seed_logs/mote_cub_seed1994_2026-07-02_0859.log",
      "average_accuracy_cnn": 91.66,
      "last_accuracy_cnn": 87.11,
      "forgetting_cnn": 5.407777777777781,
      "top1_curve": [
        97.96,
        97.55,
        94.64,
        92.37,
        91.71,
        90.81,
        88.91,
        87.73,
        87.81,
        87.11
      ],
      "top5_curve": [
        100.0,
        99.66,
        99.37,
        99.11,
        99.25,
        99.09,
        98.85,
        98.62,
        98.51,
        98.33
      ]
    },
    {
      "seed": 1995,
      "log": "/workspace/runs/mote_cub_5seed_logs/mote_cub_seed1995_2026-07-02_0912.log",
      "average_accuracy_cnn": 90.709,
      "last_accuracy_cnn": 87.11,
      "forgetting_cnn": 4.856666666666669,
      "top1_curve": [
        96.54,
        95.31,
        92.45,
        92.35,
        91.13,
        88.99,
        88.71,
        87.49,
        87.01,
        87.11
      ],
      "top5_curve": [
        99.83,
        99.57,
        99.55,
        99.49,
        99.22,
        98.88,
        98.84,
        98.71,
        98.58,
        98.38
      ]
    }
  ],
  "mean_std": {
    "average_accuracy_cnn": {
      "mean": 91.39620000000001,
      "std": 0.421362314404118
    },
    "last_accuracy_cnn": {
      "mean": 87.172,
      "std": 0.08786353054595493
    },
    "forgetting_cnn": {
      "mean": 4.646444444444445,
      "std": 0.5002415465935174
    }
  }
}